[
    {
        "title": "2023 Sports"
    },

    {
        "id": 1,
        "question": "Which country won the 2023 Rugby World Cup, held in France?",
        "answer": "South Africa"
    },
    {
        "id": 2,
        "question": "Who won the men’s singles title at Wimbledon 2023?",
        "answer": "Carlos Alcaraz"
    },

    {
        "id": 3,
        "question": "Which nations hosted the 2023 FIFA Women’s World Cup?",
        "answer": "Australia and New Zealand"
    },


    {
        "id": 4,
        "question": "Which country won the 2023 Cricket World Cup?",
        "answer": "India"
    },

    {
        "id": 5,
        "question": "Which country won the 2023 Six Nations Championship in rugby?",
        "answer": "Ireland"
    },

    {
        "id": 6,
        "question": "Where was the 2023 Ryder Cup held?",
        "answer": "Rome, Italy"
    },


    {
        "id": 7,
        "question": "Who won the 2023 Tour de France?",
        "answer": "Jonas Vingegaard"
    },

    {
        "id": 8,
        "question": "Which horse won the 2023 Grand National?",
        "answer": "Corach Rambler"
    },



    {
        "id": 9,
        "question": "Which country hosted the 2023 World Athletics Championships?",
        "answer": "Hungary"
    },

    {
        "id": 10,
        "question": "Which team won the 2023 Netball World Cup?",
        "answer": "Australia"
    }
]
